lyrics/__init__.py
lyrics/config.py
lyrics/lyrics.cfg
lyrics/lyrics_in_terminal.py
lyrics/player.py
lyrics/track.py
lyrics/util.py
lyrics/window.py
lyrics_in_terminal-1.8.0.dist-info/licenses/LICENSE
lyrics_in_terminal-1.8.0.dist-info/METADATA
lyrics_in_terminal-1.8.0.dist-info/WHEEL
lyrics_in_terminal-1.8.0.dist-info/entry_points.txt
lyrics_in_terminal-1.8.0.dist-info/top_level.txt
lyrics_in_terminal-1.8.0.dist-info/RECORD
