Metadata-Version: 2.4
Name: lyrics-in-terminal
Version: 1.8.0
Summary: Command Line Lyrics fetcher from mpris media player like Spotify, VLC, Audacious
Home-page: https://github.com/Jugran/lyrics-in-terminal
Author: Samarth Jugran
Author-email: jugransamarth@gmail.com
License: MIT
Classifier: Programming Language :: Python :: 3
Classifier: License :: OSI Approved :: MIT License
Classifier: Operating System :: POSIX :: Linux
Requires-Python: >=3.7
License-File: LICENSE
Requires-Dist: dbus-python
Requires-Dist: requests
Provides-Extra: mpd
Requires-Dist: python-mpd2; extra == "mpd"
Provides-Extra: full
Requires-Dist: python-mpd2; extra == "full"
Dynamic: author
Dynamic: author-email
Dynamic: classifier
Dynamic: description
Dynamic: description-content-type
Dynamic: home-page
Dynamic: license
Dynamic: license-file
Dynamic: provides-extra
Dynamic: requires-dist
Dynamic: requires-python
Dynamic: summary
